{"https://www.greenseal.org/products-services/?category=368": {"brands": ["G.J. Nikolas & Co., Inc.", "G.J. Nikolas & Co., Inc.", "Andersen Corporation", "Andersen Corporation", "Andersen Corporation", "Andersen Corporation", "Andersen Corporation", "Andersen Corporation", "Andersen Corporation", "Andersen Corporation", "Andersen Corporation", "Andersen Corporation", "Andersen Corporation", "Andersen Corporation", "Andersen Corporation", "Andersen Corporation", "Andersen Corporation", "Andersen Corporation", "Andersen Corporation", "Andersen Corporation", "AM Technology Ltd", "Al-Jazeera Factory for Paints Co.", "Al-Jazeera Factory for Paints Co.", "Al-Jazeera Factory for Paints Co.", "Al-Jazeera Factory for Paints Co.", "Al-Jazeera Factory for Paints Co.", "Al-Jazeera Factory for Paints Co.", "Al-Jazeera Factory for Paints Co.", "Asian Paints Limited", "Renewal by Andersen", "Renewal by Andersen", "Bona US", "Diversey Inc", "Renewal by Andersen", "Renewal by Andersen", "Renewal by Andersen", "Renewal by Andersen", "Trane Company", "Master Paints and Chemical Corporation", "Jordan Sipes Paints Co. Ltd.", "Jordan Sipes Paints Co. Ltd.", "Jordan Sipes Paints Co. Ltd.", "GDB International, Inc.", "Renewal by Andersen", "Renewal by Andersen", "Buyoung Industrial Co., Ltd", "Hillyard", "Metro Paint", "Benjamin Moore & Co", "Benjamin Moore & Co", "Benjamin Moore & Co", "Benjamin Moore & Co", "Benjamin Moore & Co", "Renewal by Andersen", "Renewal by Andersen", "Asian Paints Limited", "B.B.C. Paints", "Spraylock", "PPG Architectural Coatings Canada Inc.", "PPG Architectural Coatings Canada Inc.", "PPG Architectural Coatings Canada Inc.", "PPG Architectural Coatings Canada Inc.", "PPG Architectural Coatings Canada Inc.", "KoreKote, Inc.", "Spraylock", "Spraylock", "Spraylock", "Spraylock", "Spraylock", "Spraylock", "Spraylock", "Spraylock", "Spraylock", "Spraylock", "Hillyard", "AM Technology Ltd", "Al-Jazeera Factory for Paints Co.", "Al-Jazeera Factory for Paints Co.", "Al-Jazeera Factory for Paints Co.", "Al-Jazeera Factory for Paints Co.", "Al-Jazeera Factory for Paints Co.", "Al-Jazeera Factory for Paints Co.", "Al-Jazeera Factory for Paints Co.", "Asian Paints Limited", "Renewal by Andersen", "Renewal by Andersen", "Bona US", "Diversey Inc", "Renewal by Andersen", "Renewal by Andersen", "Renewal by Andersen", "Renewal by Andersen", "Trane Company", "Master Paints and Chemical Corporation", "Jordan Sipes Paints Co. Ltd.", "Jordan Sipes Paints Co. Ltd.", "Jordan Sipes Paints Co. Ltd.", "GDB International, Inc.", "Renewal by Andersen", "Renewal by Andersen", "Buyoung Industrial Co., Ltd", "Hillyard", "Metro Paint", "Benjamin Moore & Co", "Benjamin Moore & Co", "Benjamin Moore & Co", "Benjamin Moore & Co", "Benjamin Moore & Co", "Renewal by Andersen", "Renewal by Andersen", "Asian Paints Limited", "B.B.C. Paints", "Spraylock", "PPG Architectural Coatings Canada Inc.", "PPG Architectural Coatings Canada Inc.", "PPG Architectural Coatings Canada Inc.", "PPG Architectural Coatings Canada Inc.", "PPG Architectural Coatings Canada Inc.", "KoreKote, Inc.", "Spraylock", "Spraylock", "Spraylock", "Spraylock", "Spraylock", "Spraylock", "Spraylock", "Spraylock", "Spraylock", "Spraylock", "Hillyard"], "name": "Construction Materials & Building Equipment"}, "https://www.greenseal.org/products-services/?category=370": {"brands": ["EATware Food Packaging Ltd."], "name": "Food Packaging & Paper"}, "https://www.greenseal.org/products-services/?category=365": {"brands": ["3M", "Hygeia", "Aqua ChemPacs, LLC", "Aqua ChemPacs, LLC", "Aqua ChemPacs, LLC", "Aqua ChemPacs, LLC", "Ipax Atlantic", "Racine Industries, Inc.", "SynergyLabs", "Staples, Inc.", "Staples, Inc.", "Ultra Chem Labs", "Ultra Chem Labs", "Ultra Chem Labs"], "name": "Household Cleaning Products, Industrial & Institutional Cleaning Products"}, "https://www.greenseal.org/products-services/?category=364": {"brands": ["Multi-Clean", "Multi-Clean", "Ridley's Vacuum and Janitorial Supply", "Stratus Building Solutions", "Stratus Building Solutions", "Multi-Clean", "Multi-Clean", "Ridley's Vacuum and Janitorial Supply", "Multi-Clean", "Pro-Link, Inc.", "Pro-Link, Inc.", "Pro-Link, Inc.", "Pro-Link, Inc.", "Ridley's Vacuum and Janitorial Supply", "Ridley's Vacuum and Janitorial Supply", "Multi-Clean", "Multi-Clean", "Stratus Building Solutions", "Ridley's Vacuum and Janitorial Supply", "Stratus Building Solutions", "Stratus Building Solutions", "3M", "3M", "3M", "3M", "3M", "3M", "3M", "3M", "3M", "3M", "3M", "3M", "3M", "3M", "3M", "3M", "3M", "3M", "WAXIE Sanitary Supply", "Ecolab", "Aqua ChemPacs, LLC", "Aqua ChemPacs, LLC", "Aqua ChemPacs, LLC", "Aqua ChemPacs, LLC", "Aqua ChemPacs, LLC", "Aqua ChemPacs, LLC", "Aqua ChemPacs, LLC", "Aqua ChemPacs, LLC", "Aqua ChemPacs, LLC", "National Chemical Laboratories, Inc.", "National Chemical Laboratories, Inc.", "Pak-It", "Pak-It", "Consolidated Chemical Works", "Diversey Inc", "Annihilare/Annihilyte", "Annihilare/Annihilyte", "Von Schrader Company", "Von Schrader Company", "M.D. Stetson Company", "WORX Environmental Products Inc.", "Pak-It", "Spartan Chemical Company, Inc.", "Clenetech, LLC", "Clenetech, LLC", "Clenetech, LLC", "Zing International", "Stratus Building Solutions", "3M", "3M", "3M", "3M", "3M", "3M", "3M", "3M", "3M", "3M", "3M", "3M", "3M", "3M", "3M", "3M", "3M", "3M", "WAXIE Sanitary Supply", "Ecolab", "Aqua ChemPacs, LLC", "Aqua ChemPacs, LLC", "Aqua ChemPacs, LLC", "Aqua ChemPacs, LLC", "Aqua ChemPacs, LLC", "Aqua ChemPacs, LLC", "Aqua ChemPacs, LLC", "Aqua ChemPacs, LLC", "Aqua ChemPacs, LLC", "National Chemical Laboratories, Inc.", "National Chemical Laboratories, Inc.", "Pak-It", "Pak-It", "Consolidated Chemical Works", "Diversey Inc", "Annihilare/Annihilyte", "Annihilare/Annihilyte", "Von Schrader Company", "Von Schrader Company", "M.D. Stetson Company", "WORX Environmental Products Inc.", "Pak-It", "Spartan Chemical Company, Inc.", "Clenetech, LLC", "Clenetech, LLC", "Clenetech, LLC", "Zing International"], "name": "Industrial & Institutional Cleaning Products"}, "https://www.greenseal.org/products-services/?category=369": {"brands": ["Neenah Paper", "Neenah Paper", "Neenah Paper", "Boise", "Boise", "Boise", "Boise", "Boise", "Boise", "Boise", "Neenah Paper", "Neenah Paper", "Neenah Paper", "Neenah Paper", "Neenah Paper", "Neenah Paper", "Neenah Paper", "Neenah Paper", "Neenah Paper", "Neenah Paper", "Neenah Paper", "Neenah Paper", "Neenah Paper", "Neenah Paper", "Neenah Paper", "Neenah Paper", "Neenah Paper", "Neenah Paper", "Neenah Paper", "PT Pabrik Kertas Tjiwi Kimia Tbk", "PT Pabrik Kertas Tjiwi Kimia Tbk", "Neenah Paper", "Mohawk", "Mohawk", "Mohawk", "Mohawk", "Mohawk", "Neenah Paper", "Neenah Paper", "Office Depot", "Office Depot", "Office Depot", "Office Depot", "Neenah Paper", "PT Pabrik Kertas Tjiwi Kimia Tbk", "PT Pabrik Kertas Tjiwi Kimia Tbk", "Neenah Paper", "Neenah Paper", "Neenah Paper", "Neenah Paper", "Neenah Paper", "Neenah Paper", "Neenah Paper", "Neenah Paper", "Mohawk", "Mohawk", "Neenah Paper", "Neenah Paper", "Neenah Paper", "Neenah Paper", "Neenah Paper", "Neenah Paper", "Neenah Paper", "Neenah Paper", "Neenah Paper", "Neenah Paper", "PT Pabrik Kertas Tjiwi Kimia Tbk", "PT Pabrik Kertas Tjiwi Kimia Tbk", "Neenah Paper", "Mohawk", "Mohawk", "Mohawk", "Mohawk", "Mohawk", "Neenah Paper", "Neenah Paper", "Office Depot", "Office Depot", "Office Depot", "Office Depot", "Neenah Paper", "PT Pabrik Kertas Tjiwi Kimia Tbk", "PT Pabrik Kertas Tjiwi Kimia Tbk", "Neenah Paper", "Neenah Paper", "Neenah Paper", "Neenah Paper", "Neenah Paper", "Neenah Paper", "Neenah Paper", "Neenah Paper", "Mohawk", "Mohawk", "Neenah Paper"], "name": "Printing & Writing Paper"}, "https://www.greenseal.org/products-services/?category=366": {"brands": ["Royal Corporation", "WAXIE Sanitary Supply", "WAXIE Sanitary Supply", "WAXIE Sanitary Supply", "WAXIE Sanitary Supply", "WAXIE Sanitary Supply", "WAXIE Sanitary Supply", "WAXIE Sanitary Supply", "WAXIE Sanitary Supply", "WAXIE Sanitary Supply", "von Drehle", "Essendant", "Essendant", "Essendant", "Essendant", "Essendant", "Essendant", "Essendant", "Georgia-Pacific Consumer Products LP", "North American Corporation", "North American Corporation", "Cascades Tissue Group", "Cascades Tissue Group", "Cascades Tissue Group", "Cascades Tissue Group", "Cascades Tissue Group", "Cascades Tissue Group", "Cascades Tissue Group", "Cascades Tissue Group", "Cascades Tissue Group", "Cascades Tissue Group", "Cascades Tissue Group", "Cascades Tissue Group", "Cascades Tissue Group", "Cascades Tissue Group", "Cascades Tissue Group", "Cascades Tissue Group", "Cascades Tissue Group", "Cascades Tissue Group", "Cascades Tissue Group", "Cascades Tissue Group", "Cascades Tissue Group", "Cascades Tissue Group", "Cascades Tissue Group", "Cascades Tissue Group", "Cascades Tissue Group", "Cascades Tissue Group", "Cascades Tissue Group", "Cascades Tissue Group", "Cascades Tissue Group", "Cascades Tissue Group", "Cascades Tissue Group", "Cascades Tissue Group", "Cascades Tissue Group", "Cascades Tissue Group", "Cascades Tissue Group", "Cascades Tissue Group", "Cascades Tissue Group", "Cascades Tissue Group", "Cascades Tissue Group", "W. W. Grainger, Inc.", "W. W. Grainger, Inc.", "W. W. Grainger, Inc.", "W. W. Grainger, Inc.", "W. W. Grainger, Inc.", "von Drehle", "von Drehle", "Fabrica de Papel San Francisco", "Fabrica de Papel San Francisco", "Fabrica de Papel San Francisco", "Fabrica de Papel San Francisco", "Fabrica de Papel San Francisco", "Fabrica de Papel San Francisco", "Fabrica de Papel San Francisco", "The United Group", "The United Group", "The United Group", "The United Group", "Dickson Enterprises, Inc.", "Ferguson - Westcraft", "North American Corporation", "Cascades Tissue Group", "Cascades Tissue Group", "Cascades Tissue Group", "Cascades Tissue Group", "Cascades Tissue Group", "Cascades Tissue Group", "Cascades Tissue Group", "Cascades Tissue Group", "Cascades Tissue Group", "Cascades Tissue Group", "Cascades Tissue Group", "Cascades Tissue Group", "Cascades Tissue Group", "Cascades Tissue Group", "Cascades Tissue Group", "Cascades Tissue Group", "Cascades Tissue Group", "Cascades Tissue Group", "Cascades Tissue Group", "Cascades Tissue Group", "Cascades Tissue Group", "Cascades Tissue Group", "Cascades Tissue Group", "Cascades Tissue Group", "Cascades Tissue Group", "Cascades Tissue Group", "Cascades Tissue Group", "Cascades Tissue Group", "Cascades Tissue Group", "Cascades Tissue Group", "Cascades Tissue Group", "Cascades Tissue Group", "Cascades Tissue Group", "Cascades Tissue Group", "Cascades Tissue Group", "Cascades Tissue Group", "Cascades Tissue Group", "Cascades Tissue Group", "Cascades Tissue Group", "W. W. Grainger, Inc.", "W. W. Grainger, Inc.", "W. W. Grainger, Inc.", "W. W. Grainger, Inc.", "W. W. Grainger, Inc.", "von Drehle", "von Drehle", "Fabrica de Papel San Francisco", "Fabrica de Papel San Francisco", "Fabrica de Papel San Francisco", "Fabrica de Papel San Francisco", "Fabrica de Papel San Francisco", "Fabrica de Papel San Francisco", "Fabrica de Papel San Francisco", "The United Group", "The United Group", "The United Group", "The United Group", "Dickson Enterprises, Inc.", "Ferguson - Westcraft"], "name": "Sanitary Paper Products"}}